ssb_libtest5/__init__.py
ssb_libtest5/__main__.py
ssb_libtest5/functions.py
ssb_libtest5/py.typed
ssb_libtest5-0.0.2.dist-info/LICENSE
ssb_libtest5-0.0.2.dist-info/METADATA
ssb_libtest5-0.0.2.dist-info/WHEEL
ssb_libtest5-0.0.2.dist-info/entry_points.txt
ssb_libtest5-0.0.2.dist-info/RECORD
