Metadata-Version: 2.3
Name: ssb-libtest5
Version: 0.0.2
Summary: SSB Libtest5
License: MIT
Author: Olena Ievdochenko
Author-email: stud-olena@ssb.no
Maintainer: Statistics Norway, Population statistics Department (320)
Requires-Python: >=3.10,<4.0
Classifier: Development Status :: 4 - Beta
Classifier: License :: OSI Approved :: MIT License
Classifier: Programming Language :: Python :: 3
Classifier: Programming Language :: Python :: 3.10
Classifier: Programming Language :: Python :: 3.11
Classifier: Programming Language :: Python :: 3.12
Classifier: Programming Language :: Python :: 3.13
Requires-Dist: click (>=8.0.1)
Project-URL: Changelog, https://github.com/statisticsnorway/ssb-libtest5/releases
Project-URL: Documentation, https://statisticsnorway.github.io/ssb-libtest5
Project-URL: Homepage, https://github.com/statisticsnorway/ssb-libtest5
Project-URL: Repository, https://github.com/statisticsnorway/ssb-libtest5
